utils3d/__init__.py
utils3d/pctodepthimage.py
utils3d-0.1.2.dist-info/LICENSE
utils3d-0.1.2.dist-info/METADATA
utils3d-0.1.2.dist-info/WHEEL
utils3d-0.1.2.dist-info/RECORD
