Metadata-Version: 2.1
Name: utils3d
Version: 0.1.2
Summary: A package for 3D utilities!
License: MIT
Author: Kalash Jain
Requires-Python: >=3.8,<4.0
Classifier: License :: OSI Approved :: MIT License
Classifier: Programming Language :: Python :: 3
Classifier: Programming Language :: Python :: 3.8
Classifier: Programming Language :: Python :: 3.9
Classifier: Programming Language :: Python :: 3.10
Classifier: Programming Language :: Python :: 3.11
Classifier: Programming Language :: Python :: 3.12
Requires-Dist: addict
Requires-Dist: jupyter (>=1.0.0,<2.0.0)
Requires-Dist: matplotlib (>=3)
Requires-Dist: numpy (>1.18)
Requires-Dist: open3d (>=0.13.0,<0.14.0)
Requires-Dist: pandas (>=1.0)
Requires-Dist: pillow (>=9.3.0)
Requires-Dist: pyquaternion
Requires-Dist: pyyaml (>=5.4.1)
Requires-Dist: scikit-learn (>=0.21)
Requires-Dist: tqdm
